fedwire/__init__.py
fedwire/format.py
fedwire/generator.py
fedwire-0.1.2.dist-info/LICENSE
fedwire-0.1.2.dist-info/METADATA
fedwire-0.1.2.dist-info/WHEEL
fedwire-0.1.2.dist-info/top_level.txt
fedwire-0.1.2.dist-info/RECORD
