Metadata-Version: 2.1
Name: fedwire
Version: 0.1.2
Summary: A python package that implements an interface toread/write files for the Fedwire Funds Service
Provides-Extra: dev
Requires-Dist: coverage (==4.0.3) ; extra == 'dev'
Requires-Dist: flake8 (==3.2.1) ; extra == 'dev'
Requires-Dist: flake8-per-file-ignores ; extra == 'dev'
